process_monitoring/__init__.py
process_monitoring/monitor.py
process_monitoring/notify.py
process_monitoring/show_pid.py
process_monitoring_package-0.0.3.dist-info/LICENSE
process_monitoring_package-0.0.3.dist-info/METADATA
process_monitoring_package-0.0.3.dist-info/WHEEL
process_monitoring_package-0.0.3.dist-info/top_level.txt
process_monitoring_package-0.0.3.dist-info/RECORD
